AUTHORS.rst
CONTRIBUTING.rst
HISTORY.rst
LICENSE
MANIFEST.in
README.rst
setup.cfg
setup.py
BuildChecker/BuildChecker.py
BuildChecker/__init__.py
BuildChecker/cli.py
BuildChecker.egg-info/PKG-INFO
BuildChecker.egg-info/SOURCES.txt
BuildChecker.egg-info/dependency_links.txt
BuildChecker.egg-info/entry_points.txt
BuildChecker.egg-info/not-zip-safe
BuildChecker.egg-info/requires.txt
BuildChecker.egg-info/top_level.txt
docs/Makefile
docs/authors.rst
docs/conf.py
docs/contributing.rst
docs/history.rst
docs/index.rst
docs/installation.rst
docs/make.bat
docs/readme.rst
docs/usage.rst
tests/__init__.py
tests/test_BuildChecker.py