Metadata-Version: 1.1
Name: BuildChecker
Version: 0.1.1
Summary: Helps to get notification when building your application. Used mainly while training your deep neural network.
Home-page: https://github.com/ashwin1992/BuildChecker
Author: Ashwin Raju
Author-email: ashwinraju101@gmail.com
License: Apache Software License 2.0
Keywords: BuildChecker
Platform: UNKNOWN
Classifier: Development Status :: 2 - Pre-Alpha
Classifier: Intended Audience :: Developers
Classifier: License :: OSI Approved :: Apache Software License
Classifier: Natural Language :: English
Classifier: Programming Language :: Python :: 2
Classifier: Programming Language :: Python :: 2.6
Classifier: Programming Language :: Python :: 2.7
Classifier: Programming Language :: Python :: 3
Classifier: Programming Language :: Python :: 3.3
Classifier: Programming Language :: Python :: 3.4
Classifier: Programming Language :: Python :: 3.5
